{
  "application": {
    "name": "ESED_CustomerPreferencesManagement_UCA_IH_Publisher",
    "project": "CustomerPreferencesManagement",
    "brokerSchema": "com.abs.uca.customerPreferencesManagement",
    "flow": "ESED_CustomerPreferencesManagement_UCA_IH_Publisher",
    "identifier": "customer_preferences_management",
    "source": "UCA",
    "version": "1.0.1.001"
  },
  "kafkaConsumer": {
    "topicName": "IAUC_C02_DEV_CFMS_AGGREGATE"
  },
  "kafkaProducer": {
    "topicName": "ESED_C01_CustomerPreferencesManagement"
  },
  "transformer": {
    "name": "ESED_CFMS_CMM_Transformer"
  },
  "audit": {
    "inputMessageId": "InputRoot.JSON.Data.aggregateId"
  }
}